Metadata-Version: 1.0
Name: nd-project
Version: 9.9.7
Summary: HELLO DESCRIPTION FTW!
Home-page: UNKNOWN
Author: Nicola Dobner
Author-email: UNKNOWN
License: UNKNOWN
Platform: UNKNOWN
